family_parkrun/__init__.py
family_parkrun/download.py
family_parkrun/event.py
family_parkrun/html_construct.py
family_parkrun/page.html
family_parkrun/runner.py
family_parkrun/style.css
family_parkrun/times.py
family_parkrun-0.1.0.dist-info/entry_points.txt
family_parkrun-0.1.0.dist-info/LICENSE
family_parkrun-0.1.0.dist-info/WHEEL
family_parkrun-0.1.0.dist-info/METADATA
family_parkrun-0.1.0.dist-info/RECORD
