Metadata-Version: 2.3
Name: family_parkrun
Version: 0.1.0
Summary: Generate a summary of the Parkrun performances of a group of people.
Author: Tom Fryers
Requires-Python: >=3.9
Classifier: Development Status :: 4 - Beta
Classifier: Programming Language :: Python :: 3
Classifier: License :: OSI Approved :: GNU General Public License v3 or later (GPLv3+)
Classifier: Operating System :: OS Independent
Requires-Dist: bs4
Project-URL: Home, https://gitlab.com/Tom_Fryers/family-parkrun-summary
